pgjq_client/client.py
pgjq_client/example.py
pgjq_client-0.1.2.dist-info/LICENSE
pgjq_client-0.1.2.dist-info/METADATA
pgjq_client-0.1.2.dist-info/WHEEL
pgjq_client-0.1.2.dist-info/top_level.txt
pgjq_client-0.1.2.dist-info/RECORD
