Metadata-Version: 2.2
Name: pgjq-client
Version: 0.1.2
Summary: PGJobQueue Python Client
Requires-Python: >=3.12
License-File: LICENSE
Requires-Dist: asyncpg>=0.30.0
Requires-Dist: devtools>=0.12.2
Requires-Dist: python-dotenv>=1.0.1
